fastdiff/__init__.py
fastdiff/_base.py
fastdiff/_native.py
fastdiff/compare.py
fastdiff/fastdiff.wasm
fastdiff-0.3.0.dist-info/LICENSE
fastdiff-0.3.0.dist-info/METADATA
fastdiff-0.3.0.dist-info/WHEEL
fastdiff-0.3.0.dist-info/top_level.txt
fastdiff-0.3.0.dist-info/RECORD
