Metadata-Version: 2.1
Name: fastdiff
Version: 0.3.0
Summary: A fast native implementation of diff algorithm with a pure python fallback
Home-page: https://github.com/syrusakbary/fastdiff
Author: Syrus Akbary
Author-email: me@syrusakbary.com
License: MIT license
Keywords: fastdiff
Platform: UNKNOWN
Classifier: Development Status :: 2 - Pre-Alpha
Classifier: Intended Audience :: Developers
Classifier: License :: OSI Approved :: MIT License
Classifier: Natural Language :: English
Classifier: Programming Language :: Python :: 2
Classifier: Programming Language :: Python :: 2.7
Classifier: Programming Language :: Python :: 3
Classifier: Programming Language :: Python :: 3.4
Classifier: Programming Language :: Python :: 3.5
Classifier: Programming Language :: Python :: 3.6
Classifier: Programming Language :: Python :: 3.7
Requires-Dist: wasmer (>=1.0.0)
Requires-Dist: wasmer-compiler-cranelift (>=1.0.0)
